Workbook

Sheet Cover & Notes
B2: UNITED SPIRITS LIMITED (Diageo India)
B3: Fixed Asset Schedules - Property, Plant & Equipment (PPE), Capital Work-in-Progress (CWIP) & Right-of-Use (ROU) assets
B4: Standalone basis | All figures in Rs crore | Financial year ending 31 March
B7: SCOPE
B8: Historical actuals: FY2022 to FY2026 (5 years). Forecast: FY2027E to FY2030E (4 years).
B9: Three schedules are built as roll-forwards and linked: cash capex flows into CWIP, is capitalised into
B10: PPE, and is depreciated; ROU assets follow a separate lease roll-forward under Ind AS 116.
B12: HOW TO USE
B13: Blue figures = inputs / reported hardcodes you can change. Black figures = formulas.
B14: Historical columns are shaded blue; forecast columns are shaded green.
B15: All forecast drivers live on the 'Assumptions' tab - change them to flex the model.
B17: DATA SOURCES (primary)
... B36: Assumptions | PPE Schedule | CWIP Schedule | ROU Schedule | Summary

Sheet Assumptions
A1: ASSUMPTIONS & FORECAST DRIVERS (edit the blue cells)
A3: (Rs crore unless stated) | C3: FY2022 | D3: FY2023 | E3: FY2024 | F3: FY2025 | G3: FY2026 | H3: FY2027E | I3: FY2028E | J3: FY2029E | K3: FY2030E
A4: Net sales value (NSV) - forecast driver base | G4: 12467 | H4: =G4*(1+H5) | I4: =H4*(1+I5) | J4: =I4*(1+J5) | K4: =J4*(1+K5)
A5: NSV growth (YoY) | H5: 0.09 | I5: 0.09 | J5: 0.09 | K5: 0.09
A6: Cash capex as % of NSV | G6: =181/G4 | H6: 0.015 | I6: 0.015 | J6: 0.015 | K6: 0.015
A7: PPE depreciation as % of opening net block | H7: 0.13 | I7: 0.13 | J7: 0.13 | K7: 0.13
A8: ROU additions as % of NSV | H8: 0.013 | I8: 0.013 | J8: 0.013 | K8: 0.013
A9: ROU amortisation as % of (opening + 1/2 additions) | H9: 0.3 | I9: 0.3 | J9: 0.3 | K9: 0.3
A12: Notes:
A13: - NSV FY2026 base (Rs 12,467 cr) is USL's reported FY26 net sales value; grown by the YoY% to drive forecast capex & lease additions.
A14: - Cash capex (% of NSV) feeds CWIP additions; CWIP is capitalised into PPE the same year (CWIP held ~flat).
A15: - PPE depreciation % of opening net block is calibrated to FY2024-FY2026 actuals (~12-13%).
A16: - ROU additions (% of NSV) and amortisation (% of opening + half additions) reflect short-life plant/equipment leases.
A17: - All blue cells are editable inputs; change any driver and the schedules + Summary update automatically.

Sheet PPE Schedule
A1: PROPERTY, PLANT & EQUIPMENT (PPE) SCHEDULE - Standalone (Rs crore)
A3: (Rs crore) | C3: FY2022 | D3: FY2023 | E3: FY2024 | F3: FY2025 | G3: FY2026 | H3: FY2027E | I3: FY2028E | J3: FY2029E | K3: FY2030E
A4: Net block roll-forward
A5: Opening net block | D5: =C10 | E5: =D10 | F5: =E10 | G5: =F10 | H5: =G10 | I5: =H10 | J5: =I10 | K5: =J10
A6: (+) Additions (capitalised from CWIP) | D6: 135 | E6: 126 | F6: 126 | G6: 179 | H6: ='CWIP Schedule'!H7 | I6: ='CWIP Schedule'!I7 | J6: ='CWIP Schedule'!J7 | K6: ='CWIP Schedule'!K7
A7: (-) Depreciation | D7: 129 | E7: 121 | F7: 113 | G7: 112 | H7: =Assumptions!H7*H5 | I7: =Assumptions!I7*I5 | J7: =Assumptions!J7*J5 | K7: =Assumptions!K7*K5
A8: (-) Impairment | D8: 109 | E8: 20 | F8: 0 | G8: 0 | H8: 0 | I8: 0 | J8: 0 | K8: 0
A9: (-) Disposals, transfers & reclassifications (net) | D9: 120 | E9: 119 | F9: 7 | G9: 86 | H9: 0 | I9: 0 | J9: 0 | K9: 0
A10: Closing net block | C10: 1201 | D10: =D5+D6-D7-D8-D9 | E10: =E5+E6-E7-E8-E9 | F10: =F5+F6-F7-F8-F9 | G10: =G5+G6-G7-G8-G9 | H10: =H5+H6-H7-H8-H9 | I10: =I5+I6-I7-I8-I9 | J10: =J5+J6-J7-J8-J9 | K10: =K5+K6-K7-K8-K9
A12: Memo: reported gross block & accumulated depreciation
A13: Gross block (closing) | C13: 2202 | D13: 1988 | E13: 1869 | F13: 1915 | G13: n/a
A14: Accumulated depreciation & impairment (closing) | C14: 1001 | D14: 1010 | E14: 1025 | F14: 1065 | G14: n/a
A15: Net block (check = gross - acc. dep.) | C15: =C13-C14 | D15: =D13-D14 | E15: =E13-E14 | F15: =F13-F14
A17: Checks
A18: Implied depreciation % of opening net block | D18: =D7/D5 | E18: =E7/E5 | F18: =F7/F5 | G18: =G7/G5 | H18: =H7/H5 | I18: =I7/I5 | J18: =J7/J5 | K18: =K7/K5
A19: Net block memo vs roll-forward (should be 0) | C19: =C15-C10 | D19: =D15-D10 | E19: =E15-E10 | F19: =F15-F10
A20: FY26 PPE depreciation & disposal/transfer split are estimates (full FY26 notes pending).

Sheet CWIP Schedule
A1: CAPITAL WORK-IN-PROGRESS (CWIP) SCHEDULE - Standalone (Rs crore)
A3: (Rs crore) | C3: FY2022 | D3: FY2023 | E3: FY2024 | F3: FY2025 | G3: FY2026 | H3: FY2027E | I3: FY2028E | J3: FY2029E | K3: FY2030E
A4: CWIP roll-forward
A5: Opening CWIP | D5: =C8 | E5: =D8 | F5: =E8 | G5: =F8 | H5: =G8 | I5: =H8 | J5: =I8 | K5: =J8
A6: (+) Additions (capital expenditure incurred) | D6: 114 | E6: 96 | F6: 161 | G6: 179 | H6: =Assumptions!H4*Assumptions!H6 | I6: =Assumptions!I4*Assumptions!I6 | J6: =Assumptions!J4*Assumptions!J6 | K6: =Assumptions!K4*Assumptions!K6
A7: (-) Capitalised to PPE / intangibles | D7: 135 | E7: 126 | F7: 126 | G7: 181 | H7: =H6 | I7: =I6 | J7: =J6 | K7: =K6
A8: Closing CWIP | C8: 88 | D8: =D5+D6-D7 | E8: =E5+E6-E7 | F8: =F5+F6-F7 | G8: =G5+G6-G7 | H8: =H5+H6-H7 | I8: =I5+I6-I7 | J8: =J5+J6-J7 | K8: =K5+K6-K7
A10: Checks
A11: Cash capex (= additions) | D11: =D6 | E11: =E6 | F11: =F6 | G11: =G6 | H11: =H6 | I11: =I6 | J11: =J6 | K11: =K6
A12: FY26 additions/capitalised tie to reported cash capex (~Rs 181 cr); CWIP held ~flat in forecast.

Sheet ROU Schedule
A1: RIGHT-OF-USE (ROU) ASSETS SCHEDULE - Standalone, Ind AS 116 (Rs crore)
A3: (Rs crore) | C3: FY2022 | D3: FY2023 | E3: FY2024 | F3: FY2025 | G3: FY2026 | H3: FY2027E | I3: FY2028E | J3: FY2029E | K3: FY2030E
A4: ROU asset roll-forward
A5: Opening ROU assets | D5: =C9 | E5: =D9 | F5: =E9 | G5: =F9 | H5: =G9 | I5: =H9 | J5: =I9 | K5: =J9
A6: (+) Additions & remeasurements | D6: 86 | E6: 184 | F6: 394 | G6: 82 | H6: =Assumptions!H4*Assumptions!H8 | I6: =Assumptions!I4*Assumptions!I8 | J6: =Assumptions!J4*Assumptions!J8 | K6: =Assumptions!K4*Assumptions!K8
A7: (-) Amortisation (depreciation of ROU) | D7: 130 | E7: 129 | F7: 147 | G7: 158 | H7: =Assumptions!H9*(H5+0.5*H6) | I7: =Assumptions!I9*(I5+0.5*I6) | J7: =Assumptions!J9*(J5+0.5*J6) | K7: =Assumptions!K9*(K5+0.5*K6)
A8: (-) Terminations, transfers & other (net) | D8: 44 | E8: 1 | F8: 17 | G8: 0 | H8: 0 | I8: 0 | J8: 0 | K8: 0
A9: Closing ROU assets | C9: 261 | D9: =D5+D6-D7-D8 | E9: =E5+E6-E7-E8 | F9: =F5+F6-F7-F8 | G9: =G5+G6-G7-G8 | H9: =H5+H6-H7-H8 | I9: =I5+I6-I7-I8 | J9: =J5+J6-J7-J8 | K9: =K5+K6-K7-K8
A11: Memo: lease economics (reported)
A12: Lease liabilities (closing) | C12: 264 | D12: 182 | E12: 240 | F12: 480
A13: Interest on lease liabilities (P&L) | E13: 21 | F13: 40 | G13: 37
A14: Principal repayment of lease liabilities (CF) | E14: 126 | F14: 137 | G14: 143
A16: Checks
A17: Implied ROU amortisation % of opening | D17: =D7/D5 | E17: =E7/E5 | F17: =F7/F5 | G17: =G7/G5 | H17: =H7/H5 | I17: =I7/I5 | J17: =J7/J5 | K17: =K7/K5
A18: FY26 ROU additions/amortisation are estimates (full FY26 lease note pending); closing Rs 381 cr is reported.

Sheet Summary
A1: SUMMARY - PPE, CWIP & ROU | United Spirits (Standalone, Rs crore)
A3: (Rs crore) | C3: FY2022 | D3: FY2023 | E3: FY2024 | F3: FY2025 | G3: FY2026 | H3: FY2027E | I3: FY2028E | J3: FY2029E | K3: FY2030E
A4: Closing balances (Balance Sheet)
A5: Property, plant & equipment (net) | C5: ='PPE Schedule'!C10 | D5: ='PPE Schedule'!D10 | E5: ='PPE Schedule'!E10 | F5: ='PPE Schedule'!F10 | G5: ='PPE Schedule'!G10 | H5: ='PPE Schedule'!H10 | I5: ='PPE Schedule'!I10 | J5: ='PPE Schedule'!J10 | K5: ='PPE Schedule'!K10
A6: Right-of-use assets | C6: ='ROU Schedule'!C9 | D6: ='ROU Schedule'!D9 | E6: ='ROU Schedule'!E9 | F6: ='ROU Schedule'!F9 | G6: ='ROU Schedule'!G9 | H6: ='ROU Schedule'!H9 | I6: ='ROU Schedule'!I9 | J6: ='ROU Schedule'!J9 | K6: ='ROU Schedule'!K9
A7: Capital work-in-progress | C7: ='CWIP Schedule'!C8 | D7: ='CWIP Schedule'!D8 | E7: ='CWIP Schedule'!E8 | F7: ='CWIP Schedule'!F8 | G7: ='CWIP Schedule'!G8 | H7: ='CWIP Schedule'!H8 | I7: ='CWIP Schedule'!I8 | J7: ='CWIP Schedule'!J8 | K7: ='CWIP Schedule'!K8
A8: Total PPE + ROU + CWIP | C8: =SUM(C5:C7) | D8: =SUM(D5:D7) | E8: =SUM(E5:E7) | F8: =SUM(F5:F7) | G8: =SUM(G5:G7) | H8: =SUM(H5:H7) | I8: =SUM(I5:I7) | J8: =SUM(J5:J7) | K8: =SUM(K5:K7)
A10: Flows (P&L / Cash flow linkage)
A11: Cash capex (PPE/CWIP) | C11: ='CWIP Schedule'!C6 | D11: ='CWIP Schedule'!D6 | E11: ='CWIP Schedule'!E6 | F11: ='CWIP Schedule'!F6 | G11: ='CWIP Schedule'!G6 | H11: ='CWIP Schedule'!H6 | I11: ='CWIP Schedule'!I6 | J11: ='CWIP Schedule'!J6 | K11: ='CWIP Schedule'!K6
A12: PPE depreciation | C12: ='PPE Schedule'!C7 | D12: ='PPE Schedule'!D7 | E12: ='PPE Schedule'!E7 | F12: ='PPE Schedule'!F7 | G12: ='PPE Schedule'!G7 | H12: ='PPE Schedule'!H7 | I12: ='PPE Schedule'!I7 | J12: ='PPE Schedule'!J7 | K12: ='PPE Schedule'!K7
A13: PPE impairment | C13: ='PPE Schedule'!C8 | D13: ='PPE Schedule'!D8 | E13: ='PPE Schedule'!E8 | F13: ='PPE Schedule'!F8 | G13: ='PPE Schedule'!G8 | H13: ='PPE Schedule'!H8 | I13: ='PPE Schedule'!I8 | J13: ='PPE Schedule'!J8 | K13: ='PPE Schedule'!K8
A14: ROU amortisation | C14: ='ROU Schedule'!C7 | D14: ='ROU Schedule'!D7 | E14: ='ROU Schedule'!E7 | F14: ='ROU Schedule'!F7 | G14: ='ROU Schedule'!G7 | H14: ='ROU Schedule'!H7 | I14: ='ROU Schedule'!I7 | J14: ='ROU Schedule'!J7 | K14: ='ROU Schedule'!K7
A15: Total depreciation & amortisation (PPE + ROU) | C15: =C12+C14 | D15: =D12+D14 | E15: =E12+E14 | F15: =F12+F14 | G15: =G12+G14 | H15: =H12+H14 | I15: =I12+I14 | J15: =J12+J14 | K15: =K12+K14
A17: Growth & ratios
A18: Total fixed-asset base YoY growth | D18: =IFERROR(D8/C8-1,"") | E18: =IFERROR(E8/D8-1,"") | F18: =IFERROR(F8/E8-1,"") | G18: =IFERROR(G8/F8-1,"") | H18: =IFERROR(H8/G8-1,"") | I18: =IFERROR(I8/H8-1,"") | J18: =IFERROR(J8/I8-1,"") | K18: =IFERROR(K8/J8-1,"")
