Workbook

Sheet Dashboard
A1: IC DASHBOARD — HEADLINE OUTPUTS (linked from all sheets)
A3: Metric | B3: Hexaware (Base) | C3: Siemens India (Base) | D3: Comment
A4: Base equity value (INR cr) | B4: =HEX_Valuation!C8 | C4: =SIE_Valuation!C6 | D4: Most likely case
A5: Base equity value (US$ bn) | B5: =HEX_Valuation!C9 | C5: =SIE_Valuation!C7 | D5: @FX 85
A6: Base MOIC (x) | B6: =HEX_Returns!C9 | C6: =SIE_Valuation!C10 | D6: Hexaware real; Siemens hypothetical
A7: Base gross IRR | B7: =HEX_Returns!C11 | C7: =SIE_Valuation!C12 | D7: Single-flow proxy
A8: Exit readiness (/10) | B8: 8.4 | C8: 9 | D8: Siemens higher but no control
A9: Control available to PE? | B9: YES | C9: NO | D9: Carlyle vs Siemens AG ~69%
A11: IC VERDICT | B11: HOLD & STAGGER-EXIT by ~CY2028 | C11: PASS on control

Sheet Assumptions
A1: PE EXIT MODEL — GLOBAL ASSUMPTIONS (single source of truth)
A3: Parameter | B3: Value | C3: Unit | D3: Source / Note
A4: FX rate (INR per USD) | B4: 85 | C4: INR/USD | D4: Modeling assumption FY25-26
A5: Discount rate / WACC | B5: 0.115 | C5: % | D5: Analyst estimate
A6: Terminal growth | B6: 0.045 | C6: % | D6: Analyst estimate
A8: HEXAWARE — sponsor (Carlyle)
A9: Carlyle entry EV (2021) | B9: 23200 | C9: INR cr | D9: ~US$3bn; Moneycontrol/CNBC
A10: Carlyle entry equity (2021, est.) | B10: 22000 | C10: INR cr | D10: Estimate (net cash co.)
A11: IPO OFS proceeds (Feb-2025) | B11: 8750 | C11: INR cr | D11: 100% OFS; Carlyle
A12: Hexaware exit-year EBITDA (est.) | B12: 2800 | C12: INR cr | D12: ~18% margin on ~15.5k cr rev
A13: Hexaware net cash (est.) | B13: 1500 | C13: INR cr | D13: Estimate
A14: Hexaware entry year | B14: 2021 | C14: yr | D14: Carlyle acquisition
A15: Hexaware exit year (base) | B15: 2028 | C15: yr | D15: Recommended staggered exit
A17: SIEMENS INDIA (continuing co.)
A18: Siemens exit-year PAT (est.) | B18: 1850 | C18: INR cr | D18: Continuing-ops estimate
A19: Hypothetical entry mcap (today) | B19: 130000 | C19: INR cr | D19: Jun-2026 ~1.27-1.33 lakh cr
A20: Hypothetical hold (years) | B20: 4 | C20: yr | D20: Illustrative
A22: Legend: | B22: Blue = hardcoded input
B23: Black = formula (linked)

Sheet HEX_Financials
A1: HEXAWARE TECHNOLOGIES — 5-YEAR FINANCIAL SUMMARY (CY, Dec-end)
A3: Metric (INR cr unless noted) | B3: CY21 | C3: CY22 | D3: CY23 | E3: CY24 | F3: CY25 | G3: CAGR/Note
A4: Revenue (INR cr) | B4: 7177.7 | C4: 9199.6 | D4: 10380.3 | E4: 11974.4 | F4: 13430.4 | G4: =(F4/B4)^(1/4)-1
A5: Revenue (US$ m) | B5: 970 | C5: 1156 | D5: 1257 | E5: 1429 | F5: 1537
A6: Revenue growth % (USD) | B6: n/a | C6: =C5/B5-1 | D6: =D5/C5-1 | E6: =E5/D5-1 | F6: =F5/E5-1
A7: EBITDA margin % | B7: 0.17 | C7: 0.165 | D7: 0.165 | E7: 0.17 | F7: 0.167
A8: EBITDA (INR cr) | B8: =B4*B7 | C8: =C4*C7 | D8: =D4*D7 | E8: =E4*E7 | F8: =F4*F7
A9: PAT (INR cr) | B9: 750 | C9: 820 | D9: 998 | E9: 1150 | F9: 1300 | G9: =(F9/B9)^(1/4)-1
A10: PAT margin % | B10: =B9/B4 | C10: =C9/C4 | D10: =D9/D4 | E10: =E9/E4 | F10: =F9/F4
A12: Sources: Stockopedia (INR revenue series); Hexaware/PR Newswire (USD revenue CY24=$1,429m, CY25=$1,537m); EBITDA & PAT analyst estimates.

Sheet HEX_Valuation
A1: HEXAWARE — EXIT VALUATION SCENARIOS (formula-linked to Assumptions)
A3: Input | B3: Bear | C3: Base | D3: Bull | E3: Unit/Note
A4: Exit-year EBITDA (INR cr) | B4: =Assumptions!$B$12 | C4: =Assumptions!$B$12 | D4: =Assumptions!$B$12 | E4: Linked to Assumptions
A5: Exit EV/EBITDA multiple (x) | B5: 13 | C5: 16 | D5: 20 | E5: Comps: midcap IT (de-rated 2026)
A6: Enterprise Value (INR cr) | B6: =B4*B5 | C6: =C4*C5 | D6: =D4*D5
A7: (+) Net cash (INR cr) | B7: =Assumptions!$B$13 | C7: =Assumptions!$B$13 | D7: =Assumptions!$B$13
A8: Equity Value (INR cr) | B8: =B6+B7 | C8: =C6+C7 | D8: =D6+D7
A9: Equity Value (US$ bn) | B9: =B8/Assumptions!$B$4/100 | C9: =C8/Assumptions!$B$4/100 | D9: =D8/Assumptions!$B$4/100
A11: EV/Revenue cross-check (Base ~3.0x) and DCF (WACC 11.5%, g 4.5%) support the Base equity range. Sources: ET/Nuvama multiples; analyst est.

Sheet HEX_Returns
A1: HEXAWARE — SPONSOR RETURNS (Carlyle) — formula-linked
A3: Metric | B3: Bear | C3: Base | D3: Bull | E3: Note
A4: Entry equity (INR cr, 2021) | B4: =Assumptions!$B$10 | C4: =Assumptions!$B$10 | D4: =Assumptions!$B$10
A5: IPO OFS realised (INR cr, 2025) | B5: =Assumptions!$B$11 | C5: =Assumptions!$B$11 | D5: =Assumptions!$B$11
A6: Residual stake % at exit | B6: 0.741 | C6: 0.741 | D6: 0.741
A7: Residual equity value (INR cr) | B7: =HEX_Valuation!B8*B6 | C7: =HEX_Valuation!C8*C6 | D7: =HEX_Valuation!D8*D6
A8: Total realisations (INR cr) | B8: =B5+B7 | C8: =C5+C7 | D8: =D5+D7
A9: MOIC (x) | B9: =B8/B4 | C9: =C8/C4 | D9: =D8/D4
A10: Holding period (years) | B10: 7 | C10: 7 | D10: 7
A11: Gross IRR (true, multi-flow) | B11: =IRR(B14:I14) | C11: =IRR(B15:I15) | D11: =IRR(B16:I16)
A12: Cash-flow timeline (INR cr) — for true IRR
A13: Year | B13: 2021 | C13: 2022 | D13: 2023 | E13: 2024 | F13: 2025 | G13: 2026 | H13: 2027 | I13: 2028
A14: Bear CF | B14: =-B4 | C14: 0 | D14: 0 | E14: 0 | F14: =B5 | G14: 0 | H14: 0 | I14: =B7
A15: Base CF | B15: =-C4 | C15: 0 | D15: 0 | E15: 0 | F15: =C5 | G15: 0 | H15: 0 | I15: =C7
A16: Bull CF | B16: =-D4 | C16: 0 | D16: 0 | E16: 0 | F16: =D5 | G16: 0 | H16: 0 | I16: =D7
A18: True IRR uses the full cash-flow series: 2021 entry equity outflow, 2025 IPO OFS proceeds (INR 8,750 cr), 2028 residual-stake realisation.

Sheet SIE_Financials
A1: SIEMENS LTD (INDIA) — 5-YEAR FINANCIALS (FY Oct-Sep; FY20-24 incl. Energy)
A3: Metric (INR cr) | B3: FY20 | C3: FY21 | D3: FY22 | E3: FY23 | F3: FY24 | G3: CAGR
A4: Revenue (INR cr) | B4: 9824 | C4: 13136 | D4: 16047 | E4: 19472 | F4: 22157 | G4: =(F4/B4)^(1/4)-1
A5: Revenue growth % | B5: n/a | C5: =C4/B4-1 | D5: =D4/C4-1 | E5: =E4/D4-1 | F5: =F4/E4-1
A6: PAT (INR cr) | B6: — | C6: — | D6: — | E6: — | F6: 2718
A8: Continuing operations (ex-Energy), recent quarters
A9: Period | B9: Revenue (INR cr) | C9: Growth % | D9: PAT (INR cr)
A10: Q4 FY25 (Sep-25) | B10: 5171 | C10: 0.16 | D10: 485
A11: Q1 FY26 (Dec-25) | B11: 3831 | C11: 0.14 | D11: 269
A12: Q2 FY26 (Mar-26) | B12: n/d | C12: 0.146 | D12: 355
A14: Sources: WSJ (FY20-24 revenue); Quartr (FY24 PAT ~2,718 cr); Siemens IR press releases (continuing ops quarters).

Sheet SIE_Valuation
A1: SIEMENS INDIA — EXIT VALUATION & HYPOTHETICAL RETURNS (formula-linked)
A3: Input | B3: Bear | C3: Base | D3: Bull | E3: Note
A4: Exit-year PAT (grown, INR cr) | B4: 3000 | C4: 3700 | D4: 4400 | E4: Current ~normalized PAT grown ~12-15%/yr over hold
A5: Exit P/E multiple (x) | B5: 32 | C5: 45 | D5: 52 | E5: Premium capital-goods comps (ABB/Hitachi)
A6: Equity Value (INR cr) | B6: =B4*B5 | C6: =C4*C5 | D6: =D4*D5
A7: Equity Value (US$ bn) | B7: =B6/Assumptions!$B$4/100 | C7: =C6/Assumptions!$B$4/100 | D7: =D6/Assumptions!$B$4/100
A9: Hypothetical entry mcap (INR cr) | B9: =Assumptions!$B$19 | C9: =Assumptions!$B$19 | D9: =Assumptions!$B$19
A10: MOIC (x) | B10: =B6/B9 | C10: =C6/C9 | D10: =D6/D9
A11: Hold (years) | B11: =Assumptions!$B$20 | C11: =Assumptions!$B$20 | D11: =Assumptions!$B$20
A12: Gross IRR (approx.) | B12: =(B10)^(1/B11)-1 | C12: =(C10)^(1/C11)-1 | D12: =(D10)^(1/D11)-1
A14: Note: No realistic PE control entry exists (Siemens AG ~69%). Returns illustrative on hypothetical entry at today's mcap. Already richly valued.
